on1builder/__init__.py
on1builder/__main__.py
on1builder/cli/__init__.py
on1builder/cli/config_cmd.py
on1builder/cli/run_cmd.py
on1builder/cli/status_cmd.py
on1builder/config/__init__.py
on1builder/config/loaders.py
on1builder/config/manager.py
on1builder/config/settings.py
on1builder/config/validation.py
on1builder/core/__init__.py
on1builder/core/balance_manager.py
on1builder/core/chain_worker.py
on1builder/core/main_orchestrator.py
on1builder/core/multi_chain_orchestrator.py
on1builder/core/nonce_manager.py
on1builder/core/transaction_manager.py
on1builder/engines/__init__.py
on1builder/engines/safety_guard.py
on1builder/engines/strategy_executor.py
on1builder/integrations/__init__.py
on1builder/integrations/abi_registry.py
on1builder/integrations/external_apis.py
on1builder/monitoring/__init__.py
on1builder/monitoring/market_data_feed.py
on1builder/monitoring/performance_monitor.py
on1builder/monitoring/txpool_scanner.py
on1builder/persistence/__init__.py
on1builder/persistence/db_interface.py
on1builder/persistence/db_models.py
on1builder/resources/abi/aave_flashloan_abi.json
on1builder/resources/abi/aave_pool_abi.json
on1builder/resources/abi/erc20_abi.json
on1builder/resources/abi/gas_price_oracle_abi.json
on1builder/resources/abi/sushiswap_abi.json
on1builder/resources/abi/uniswap_abi.json
on1builder/resources/contracts/IERC20.sol
on1builder/resources/contracts/SimpleFlashloan.sol
on1builder/resources/ml_models/strategy_weights.json
on1builder/resources/tokens/all_chains_tokens.json
on1builder/utils/__init__.py
on1builder/utils/cli_helpers.py
on1builder/utils/config_redactor.py
on1builder/utils/constants.py
on1builder/utils/container.py
on1builder/utils/custom_exceptions.py
on1builder/utils/error_handling.py
on1builder/utils/error_recovery.py
on1builder/utils/gas_optimizer.py
on1builder/utils/logging_config.py
on1builder/utils/memory_optimizer.py
on1builder/utils/notification_service.py
on1builder/utils/path_helpers.py
on1builder/utils/profit_calculator.py
on1builder-2.2.1.dist-info/licenses/LICENSE
on1builder-2.2.1.dist-info/METADATA
on1builder-2.2.1.dist-info/WHEEL
on1builder-2.2.1.dist-info/entry_points.txt
on1builder-2.2.1.dist-info/top_level.txt
on1builder-2.2.1.dist-info/RECORD
