Metadata-Version: 2.4
Name: on1builder
Version: 2.2.1
Summary: A high-performance, multi-chain MEV and trading bot framework.
Author-email: john0n1 <john@on1.no>
License: MIT
Project-URL: Homepage, https://github.com/john0n1/ON1Builder
Project-URL: Bug Tracker, https://github.com/john0n1/ON1Builder/issues
Keywords: blockchain,ethereum,trading,mev,arbitrage,defi,flashloan,crypto,bot,automated-trading,web3,uniswap,multi-chain,async,framework
Classifier: Development Status :: 5 - Production/Stable
Classifier: Programming Language :: Python :: 3
Classifier: Programming Language :: Python :: 3.10
Classifier: Programming Language :: Python :: 3.11
Classifier: Programming Language :: Python :: 3.12
Classifier: Programming Language :: Python :: 3.13
Classifier: Operating System :: OS Independent
Classifier: Intended Audience :: Developers
Classifier: Intended Audience :: Financial and Insurance Industry
Classifier: Topic :: Software Development :: Libraries :: Python Modules
Classifier: Topic :: Office/Business :: Financial :: Investment
Classifier: Topic :: Internet :: WWW/HTTP :: Dynamic Content
Classifier: Topic :: Software Development :: Libraries :: Application Frameworks
Classifier: Environment :: Console
Classifier: Framework :: AsyncIO
Requires-Python: >=3.10
License-File: LICENSE
Requires-Dist: aiohappyeyeballs
Requires-Dist: aiohttp
Requires-Dist: aiosignal
Requires-Dist: aiosqlite
Requires-Dist: annotated-types
Requires-Dist: attrs
Requires-Dist: Automat
Requires-Dist: bitarray
Requires-Dist: cachetools
Requires-Dist: certifi
Requires-Dist: charset-normalizer
Requires-Dist: ckzg
Requires-Dist: colorlog
Requires-Dist: constantly
Requires-Dist: cytoolz
Requires-Dist: docopt
Requires-Dist: eth-account
Requires-Dist: eth-hash
Requires-Dist: eth-keyfile
Requires-Dist: eth-keys
Requires-Dist: eth-rlp
Requires-Dist: eth-typing
Requires-Dist: eth-utils
Requires-Dist: eth_abi
Requires-Dist: frozenlist
Requires-Dist: furl
Requires-Dist: greenlet
Requires-Dist: hexbytes
Requires-Dist: hyperlink
Requires-Dist: idna
Requires-Dist: incremental
Requires-Dist: Jinja2
Requires-Dist: MarkupSafe
Requires-Dist: multidict
Requires-Dist: numpy
Requires-Dist: orderedmultidict
Requires-Dist: packaging
Requires-Dist: parsimonious
Requires-Dist: propcache
Requires-Dist: psutil
Requires-Dist: pycryptodome
Requires-Dist: pydantic
Requires-Dist: pydantic_core
Requires-Dist: pydantic-settings
Requires-Dist: python-dateutil
Requires-Dist: python-dotenv
Requires-Dist: pyunormalize
Requires-Dist: PyYAML
Requires-Dist: questionary
Requires-Dist: redo
Requires-Dist: regex
Requires-Dist: requests
Requires-Dist: rich
Requires-Dist: rlp
Requires-Dist: setuptools
Requires-Dist: simplejson
Requires-Dist: six
Requires-Dist: SQLAlchemy
Requires-Dist: toolz
Requires-Dist: Twisted
Requires-Dist: types-requests
Requires-Dist: typing-extensions
Requires-Dist: typer[all]
Requires-Dist: urllib3
Requires-Dist: web3
Requires-Dist: websockets
Requires-Dist: yarl
Requires-Dist: zope.interface
Provides-Extra: test
Requires-Dist: pytest; extra == "test"
Requires-Dist: pytest-cov; extra == "test"
Requires-Dist: pytest-asyncio; extra == "test"
Requires-Dist: coverage[toml]; extra == "test"
Provides-Extra: dev
Requires-Dist: pytest; extra == "dev"
Requires-Dist: pytest-cov; extra == "dev"
Requires-Dist: pytest-asyncio; extra == "dev"
Requires-Dist: coverage[toml]; extra == "dev"
Requires-Dist: black; extra == "dev"
Requires-Dist: isort; extra == "dev"
Requires-Dist: flake8; extra == "dev"
Requires-Dist: mypy; extra == "dev"
Requires-Dist: pre-commit; extra == "dev"
Requires-Dist: twine; extra == "dev"
Dynamic: license-file
